.VERSION
AUTHORS.rst
CONTRIBUTING.rst
HISTORY.rst
LICENSE
MANIFEST.in
Pipfile
Pipfile.lock
README.rst
USAGE.rst
dev-requirements.txt
requirements.txt
setup.cfg
setup.py
docs/Makefile
docs/authors.rst
docs/conf.py
docs/contributing.rst
docs/develop.rst
docs/history.rst
docs/index.rst
docs/installation.rst
docs/readme.rst
docs/usage.rst
lastpasslib/.VERSION
lastpasslib/AUTHORS.rst
lastpasslib/CONTRIBUTING.rst
lastpasslib/HISTORY.rst
lastpasslib/LICENSE
lastpasslib/Pipfile
lastpasslib/Pipfile.lock
lastpasslib/README.rst
lastpasslib/USAGE.rst
lastpasslib/__init__.py
lastpasslib/_version.py
lastpasslib/configuration.py
lastpasslib/datamodels.py
lastpasslib/dataschemas.py
lastpasslib/dev-requirements.txt
lastpasslib/encryption.py
lastpasslib/lastpasslib.py
lastpasslib/lastpasslibexceptions.py
lastpasslib/requirements.txt
lastpasslib/secrets.py
lastpasslib/utils.py
lastpasslib/vault.py
lastpasslib.egg-info/PKG-INFO
lastpasslib.egg-info/SOURCES.txt
lastpasslib.egg-info/dependency_links.txt
lastpasslib.egg-info/not-zip-safe
lastpasslib.egg-info/requires.txt
lastpasslib.egg-info/top_level.txt
tests/test_lastpasslib.py