Metadata-Version: 2.1
Name: lastpasslib
Version: 1.1.0
Summary: A library able to retrieve and decrypt all items in lastpass along with their change history and attachments.
Home-page: https://github.com/schubergphilis/lastpasslib
Author: Costas Tyfoxylos
Author-email: ctyfoxylos@schubergphilis.com
License: MIT
Keywords: lastpasslib lastpass read-only
Classifier: Development Status :: 4 - Beta
Classifier: Intended Audience :: Developers
Classifier: License :: OSI Approved :: MIT License
Classifier: Natural Language :: English
Classifier: Programming Language :: Python :: 3.9
License-File: LICENSE
License-File: AUTHORS.rst
Requires-Dist: requests>=2.31.0; python_version >= "3.7"
Requires-Dist: pycryptodome>=3.18.0; python_version >= "2.7" and python_version not in "3.0, 3.1, 3.2, 3.3, 3.4"
Requires-Dist: python-dateutil>=2.8.2; python_version >= "2.7" and python_version not in "3.0, 3.1, 3.2, 3.3"
Requires-Dist: backoff>=1.11.1; python_version >= "2.7" and python_version not in "3.0, 3.1, 3.2, 3.3, 3.4"
